glaredb-25.6.3.dist-info/METADATA
glaredb-25.6.3.dist-info/WHEEL
glaredb/__init__.py
glaredb/glaredb.abi3.so
glaredb-25.6.3.dist-info/RECORD
