Metadata-Version: 2.4
Name: glaredb
Version: 25.6.3
Classifier: Programming Language :: Rust
Classifier: Programming Language :: Python :: Implementation :: CPython
Classifier: Programming Language :: Python :: Implementation :: PyPy
Summary: Python bindings for GlareDB
Home-Page: https://glaredb.com
License: MIT
Requires-Python: >=3.7
Project-URL: Homepage, https://glaredb.com
